boomba/__init__.py
boomba/main.py
boomba/cli/base.py
boomba/cli/command.py
boomba/cli/description.py
boomba/core/config.py
boomba/core/constants.py
boomba/core/db.py
boomba/core/dtypes.py
boomba/core/etl.py
boomba/core/log.py
boomba/core/metadata.py
boomba/core/schedule.py
boomba/core/schema.py
boomba/exception/exc.py
boomba/template/settings.py-tpl
boomba/template/template.py
boomba/template/pipeline/extraction.py-tpl
boomba/template/pipeline/load.py-tpl
boomba/template/pipeline/schedule.py-tpl
boomba/template/pipeline/schema.py-tpl
boomba/template/pipeline/transformation.py-tpl
boomba/util/date.py
boomba/util/dependency.py
boomba/util/parse.py
boomba-0.1.0b4.dist-info/LICENSE.txt
boomba-0.1.0b4.dist-info/METADATA
boomba-0.1.0b4.dist-info/WHEEL
boomba-0.1.0b4.dist-info/entry_points.txt
boomba-0.1.0b4.dist-info/top_level.txt
boomba-0.1.0b4.dist-info/RECORD
