Metadata-Version: 2.2
Name: boomba
Version: 0.1.0b4
Summary: Light and Fast ETL Framework
Home-page: https://github.com/Baboomba/boomba
Author: SungEun An
Author-email: SungEun An <bach0918@gmail.com>
License: BSD 3-Clause License
Project-URL: repository, https://github.com/Baboomba/boomba
Classifier: Development Status :: 4 - Beta
Classifier: Intended Audience :: Developers
Classifier: License :: OSI Approved :: BSD License
Classifier: Operating System :: OS Independent
Classifier: Programming Language :: Python :: 3
Requires-Python: >=3.13
License-File: LICENSE.txt
Requires-Dist: polars
Requires-Dist: pyarrow
Requires-Dist: SQLAlchemy
Dynamic: author
Dynamic: home-page
Dynamic: requires-python
